{
	"colors": [
		"#16a085",
		"#2980b9",
		"#34495e",
		"#d35400",
		"#7f8c8d",
		"#c0392b"
	],
	"lines": [
		{
			"author": "MENDES, Jonas",
			"text": "Nunca tomou o que na cara??"
		},
		{
			"author": "MENDES, Jonas",
			"text": "Hey hi"
		},
		{
			"author": "GODOY, Gabriel",
			"text": "A Uruguaiana é o nosso vale do Silício."
		},
		{
			"author": "CHEVALLIER, Kevin",
			"text": "Pôôrrâ!"
		},
		{
			"author": "GODOY, Gabriel",
			"text": "É melhor um burro por cinco minutos, do que pra vida toda."
		},
		{
			"author": "GOMES, Rafael",
			"text": "Objeto agnóstico? Ele não acredita em Deus?"
		},
		{
			"author": "GODOY, Gabriel",
			"text": "Ali... é uma coisa a se ver..."
		},
		{
			"author": "GOMES, Rafael",
			"text": "John Papa? Não era Francisco o nome dele?"
		},
		{
			"author": "SILVEIRA, Isabella",
			"text": "Eu não tenho preparação mental para desenvolver Javascript."
		},
		{
			"author": "SILVEIRA, Isabella",
			"text": "@!%ˆ&*?#@!&$?."
		},
		{
			"author": "SILVEIRA, Isabella",
			"text": "Isso é bullying! (Criticando Java)"
		},
		{
			"author": "SILVEIRA, Isabella",
			"text": "Eu estou acostumada com null pointer cara."
		},
		{
			"author": "VACCARO, Caio",
			"text": "Can you hear me?"
		},
		{
			"author": "QUACH, Tan",
			"text": "WHY JONAS WHY"
		},
		{
			"author": "SILVEIRA, Isabella",
			"text": "Até eu to odiando Java agora, foda-se essa merda."
		},
		{
			"author": "FROTA, João Pedro",
			"text": "Hoje não dá, eu tenho a minha yoga!"
		},
		{
			"author": "SILVEIRA, Isabella",
			"text": "Isso é cabacice!"
		},
		{
			"author": "SILVEIRA, Isabella",
			"text": "Esse ficou mais atômico!"
		},
		{
			"author": "VACCARO, Caio",
			"text": "O que o Angular acredita não é importante."
		},
		{
			"author": "GODOY, Gabriel",
			"text": "Fator em inglês? Factory."
		},
		{
			"author": "PAGNONCELLI, João",
			"text": "O bem é relativo."
		},
		{
			"author": "VACCARO, Caio",
			"text": "Código não testável === Shitty code."
		},
		{
			"author": "To SILVEIRA, Isabella",
			"text": "Then you screwed up big time."
		},
		{
			"author": "GODOY, Gabriel",
			"text": "Ta todo cagado!"
		},
		{
			"author": "FROTA, João Pedro",
			"text": "Meu personal acaba 9:20!"
		},
		{
			"author": "GODOY, Gabriel",
			"text": "No build dos outros é refresco."
		}
	]
}
